sr_invoice_parser/__init__.py
sr_invoice_parser/decorators.py
sr_invoice_parser/exceptions.py
sr_invoice_parser/parser.py
sr_invoice_parser-1.0.3.dist-info/licenses/LICENSE
sr_invoice_parser-1.0.3.dist-info/WHEEL
sr_invoice_parser-1.0.3.dist-info/METADATA
sr_invoice_parser-1.0.3.dist-info/RECORD
