Metadata-Version: 2.4
Name: sr-invoice-parser
Version: 1.0.3
Summary: SR Invoice Parser is a small library(crawler) that is parsing invoices and extracting relevant information from URL. For Serbian market.
Author-email: Innovigo <hello@innovigo.co>
Requires-Python: >=3.8
Classifier: Intended Audience :: Developers
Classifier: Programming Language :: Python :: 3
Classifier: License :: OSI Approved :: MIT License
Classifier: Topic :: Software Development :: Libraries :: Python Modules
License-File: LICENSE
Requires-Dist: pytz>=2021.1
Requires-Dist: requests>=2.21.0
Requires-Dist: parsel>=1.7.0
Requires-Dist: srtools>=0.1.13
Project-URL: Home, https://github.com/Innovigo/sr-invoice-parser
Project-URL: Issues, https://github.com/Innovigo/sr-invoice-parser/issues
Project-URL: Source, https://github.com/Innovigo/sr-invoice-parser
